comeagainquestionmark/__init__.py
comeagainquestionmark/__main__.py
comeagainquestionmark/main.py
comeagainquestionmark-0.1.2.dist-info/LICENSE
comeagainquestionmark-0.1.2.dist-info/WHEEL
comeagainquestionmark-0.1.2.dist-info/METADATA
comeagainquestionmark-0.1.2.dist-info/RECORD
